locust_sse/__init__.py
locust_sse/user.py
locust_sse-0.3.1.dist-info/METADATA
locust_sse-0.3.1.dist-info/WHEEL
locust_sse-0.3.1.dist-info/licenses/LICENSE
locust_sse-0.3.1.dist-info/RECORD
