Metadata-Version: 2.4
Name: locust-sse
Version: 0.3.1
Summary: A Locust user subclass for testing Server-Sent Events (SSE) endpoints.
Project-URL: Homepage, https://github.com/Aleph-Alpha/locust-sse
Project-URL: Repository, https://github.com/Aleph-Alpha/locust-sse
License-File: LICENSE
Classifier: Development Status :: 4 - Beta
Classifier: Intended Audience :: Developers
Classifier: License :: OSI Approved :: MIT License
Classifier: Programming Language :: Python :: 3
Classifier: Programming Language :: Python :: 3.12
Classifier: Topic :: Software Development :: Testing :: Traffic Generation
Requires-Python: >=3.12
Requires-Dist: locust>=2.42.6
